setup.py
django_sslredirector.egg-info/PKG-INFO
django_sslredirector.egg-info/SOURCES.txt
django_sslredirector.egg-info/dependency_links.txt
django_sslredirector.egg-info/requires.txt
django_sslredirector.egg-info/top_level.txt
sslredirector/__init__.py
sslredirector/decorators.py
sslredirector/middleware.py