Metadata-Version: 1.0
Name: django-sslredirector
Version: 0.1.b1
Summary: A simple django application that manages http/https statuses of different views.
